touka
