Metadata-Version: 2.1
Name: touka
Version: 1.1.8
Summary: A Python wrapper for automation.
Author: Black Reaper
License: MIT
Project-URL: Discord, https://discord.gg/yzAJ3wg5S3
Platform: UNKNOWN
Classifier: Development Status :: 5 - Production/Stable
Classifier: License :: OSI Approved :: MIT License
Classifier: Intended Audience :: Other Audience
Classifier: Natural Language :: English
Classifier: Operating System :: OS Independent
Classifier: Programming Language :: Python :: 3.10
Classifier: Topic :: Home Automation
Classifier: Topic :: Utilities
Classifier: Typing :: Typed
Requires-Python: >=3.8
License-File: LICENSE
